grits/__init__.py
grits/render.py
grits/scripts/__init__.py
grits/scripts/build.py
grits/scripts/serve.py
grits/templates/__full.html
grits/templates/__partial.html
grits/templates/_dynamicRoutes.json
grits/templates/_prefetchManifest.json
grits/templates/static/vendor/mapp.min.js
grits/templates/static/vendor/rq.min.js
grits-0.5.1.dist-info/DESCRIPTION.rst
grits-0.5.1.dist-info/METADATA
grits-0.5.1.dist-info/RECORD
grits-0.5.1.dist-info/WHEEL
grits-0.5.1.dist-info/entry_points.txt
grits-0.5.1.dist-info/metadata.json
grits-0.5.1.dist-info/top_level.txt
