Metadata-Version: 2.0
Name: grits
Version: 0.5.1
Summary: Static SPA Generator
Home-page: https://github.com/numberoverzero/grits
Author: Joe Cross
Author-email: joe.mcross@gmail.com
License: MIT
Keywords: static blog spa generator
Platform: any
Classifier: Development Status :: 2 - Pre-Alpha
Classifier: Intended Audience :: Developers
Classifier: License :: OSI Approved :: MIT License
Classifier: Operating System :: OS Independent
Classifier: Programming Language :: Python
Classifier: Programming Language :: Python :: 3
Classifier: Programming Language :: Python :: 3.6
Requires-Dist: beautifulsoup4 (==4.6.0)
Requires-Dist: click (==6.7)
Requires-Dist: jinja2 (==2.9.5)
